<?xml version="1.0" encoding="UTF-8"?>
<files psalm-version="5.18.0@b113f3ed0259fd6e212d87c3df80eec95a6abf19">
  <file src="src/Extension.php">
    <DuplicateClass>
      <code>Extension</code>
    </DuplicateClass>
    <UnusedClass>
      <code>Extension</code>
    </UnusedClass>
    <UnusedParam>
      <code>$options</code>
    </UnusedParam>
  </file>
  <file src="src/FileWriter/DefaultFileWriter.php">
    <InvalidArgument>
      <code>static function (): void {
        }</code>
    </InvalidArgument>
  </file>
  <file src="src/Formatter/DefaultDurationFormatter.php">
    <InvalidOperand>
      <code><![CDATA[$duration->seconds() * 1_000 + $duration->nanoseconds() / 1_000_000]]></code>
      <code>$durationInMilliseconds - $hoursInMilliseconds</code>
      <code>$durationInMilliseconds - $hoursInMilliseconds</code>
      <code>$durationInMilliseconds / 60</code>
      <code>$durationInMilliseconds / 60</code>
      <code>($durationInMilliseconds - $hoursInMilliseconds - $minutesInMilliseconds) / 1_000</code>
    </InvalidOperand>
  </file>
  <file src="src/Logger/LoggerFactory.php">
    <MixedInferredReturnType>
      <code>Logger</code>
    </MixedInferredReturnType>
    <UndefinedClass>
      <code>Runner\Extension\ParameterCollection</code>
      <code>TextUI\Configuration\Configuration</code>
    </UndefinedClass>
    <UnusedClass>
      <code>LoggerFactory</code>
    </UnusedClass>
    <UnusedParam>
      <code>$configuration</code>
      <code>$parameters</code>
    </UnusedParam>
  </file>
  <file src="src/Reporter/NullReporter.php">
    <UnusedClass>
      <code>NullReporter</code>
    </UnusedClass>
  </file>
  <file src="src/Subscriber/Test/FinishedSubscriber.php">
    <UndefinedClass>
      <code>Event\Test\FinishedSubscriber</code>
    </UndefinedClass>
    <UnusedClass>
      <code>FinishedSubscriber</code>
    </UnusedClass>
    <UnusedParam>
      <code>$collector</code>
      <code>$event</code>
      <code>$maximumDuration</code>
      <code>$timeKeeper</code>
    </UnusedParam>
  </file>
  <file src="src/Subscriber/Test/PreparationStartedSubscriber.php">
    <UndefinedClass>
      <code>Event\Test\PreparationStartedSubscriber</code>
    </UndefinedClass>
    <UnusedClass>
      <code>PreparationStartedSubscriber</code>
    </UnusedClass>
    <UnusedParam>
      <code>$event</code>
      <code>$timeKeeper</code>
    </UnusedParam>
  </file>
  <file src="src/Subscriber/TestRunner/ExecutionFinishedSubscriber.php">
    <UndefinedClass>
      <code>Event\TestRunner\ExecutionFinishedSubscriber</code>
    </UndefinedClass>
    <UnusedClass>
      <code>ExecutionFinishedSubscriber</code>
    </UnusedClass>
    <UnusedParam>
      <code>$collector</code>
      <code>$event</code>
      <code>$logger</code>
      <code>$reporter</code>
    </UnusedParam>
  </file>
  <file src="test/EndToEnd/Version07/TestCase/Combination/SleeperTest.php">
    <PossiblyUnusedMethod>
      <code>sleepWithAfterAnnotation</code>
      <code>sleepWithAfterClassAnnotation</code>
      <code>sleepWithBeforeAnnotation</code>
      <code>sleepWithBeforeClassAnnotation</code>
    </PossiblyUnusedMethod>
  </file>
  <file src="test/EndToEnd/Version07/TestCase/WithAfterAnnotation/SleeperTest.php">
    <PossiblyUnusedMethod>
      <code>sleepWithAfterAnnotation</code>
    </PossiblyUnusedMethod>
  </file>
  <file src="test/EndToEnd/Version07/TestCase/WithAfterClassAnnotation/SleeperTest.php">
    <PossiblyUnusedMethod>
      <code>sleepWithAfterClassAnnotation</code>
    </PossiblyUnusedMethod>
  </file>
  <file src="test/EndToEnd/Version07/TestCase/WithBeforeAnnotation/SleeperTest.php">
    <PossiblyUnusedMethod>
      <code>sleepWithBeforeAnnotation</code>
    </PossiblyUnusedMethod>
  </file>
  <file src="test/EndToEnd/Version07/TestCase/WithBeforeClassAnnotation/SleeperTest.php">
    <PossiblyUnusedMethod>
      <code>sleepWithBeforeClassAnnotation</code>
    </PossiblyUnusedMethod>
  </file>
  <file src="test/EndToEnd/Version07/TestMethod/WithRunInSeparateProcessAnnotation/SleeperTest.php">
    <PossiblyUnusedMethod>
      <code>sleepWithAfterAnnotation</code>
      <code>sleepWithAfterClassAnnotation</code>
      <code>sleepWithBeforeAnnotation</code>
      <code>sleepWithBeforeClassAnnotation</code>
    </PossiblyUnusedMethod>
  </file>
  <file src="test/EndToEnd/Version08/TestCase/Combination/SleeperTest.php">
    <PossiblyUnusedMethod>
      <code>sleepWithAfterAnnotation</code>
      <code>sleepWithAfterClassAnnotation</code>
      <code>sleepWithBeforeAnnotation</code>
      <code>sleepWithBeforeClassAnnotation</code>
    </PossiblyUnusedMethod>
  </file>
  <file src="test/EndToEnd/Version08/TestCase/WithAfterAnnotation/SleeperTest.php">
    <PossiblyUnusedMethod>
      <code>sleepWithAfterAnnotation</code>
    </PossiblyUnusedMethod>
  </file>
  <file src="test/EndToEnd/Version08/TestCase/WithAfterClassAnnotation/SleeperTest.php">
    <PossiblyUnusedMethod>
      <code>sleepWithAfterClassAnnotation</code>
    </PossiblyUnusedMethod>
  </file>
  <file src="test/EndToEnd/Version08/TestCase/WithBeforeAnnotation/SleeperTest.php">
    <PossiblyUnusedMethod>
      <code>sleepWithBeforeAnnotation</code>
    </PossiblyUnusedMethod>
  </file>
  <file src="test/EndToEnd/Version08/TestCase/WithBeforeClassAnnotation/SleeperTest.php">
    <PossiblyUnusedMethod>
      <code>sleepWithBeforeClassAnnotation</code>
    </PossiblyUnusedMethod>
  </file>
  <file src="test/EndToEnd/Version08/TestMethod/WithRunInSeparateProcessAnnotation/SleeperTest.php">
    <PossiblyUnusedMethod>
      <code>sleepWithAfterAnnotation</code>
      <code>sleepWithAfterClassAnnotation</code>
      <code>sleepWithBeforeAnnotation</code>
      <code>sleepWithBeforeClassAnnotation</code>
    </PossiblyUnusedMethod>
  </file>
  <file src="test/EndToEnd/Version09/TestCase/Combination/SleeperTest.php">
    <PossiblyUnusedMethod>
      <code>sleepWithAfterAnnotation</code>
      <code>sleepWithAfterClassAnnotation</code>
      <code>sleepWithBeforeAnnotation</code>
      <code>sleepWithBeforeClassAnnotation</code>
    </PossiblyUnusedMethod>
  </file>
  <file src="test/EndToEnd/Version09/TestCase/WithAfterAnnotation/SleeperTest.php">
    <PossiblyUnusedMethod>
      <code>sleepWithAfterAnnotation</code>
    </PossiblyUnusedMethod>
  </file>
  <file src="test/EndToEnd/Version09/TestCase/WithAfterClassAnnotation/SleeperTest.php">
    <PossiblyUnusedMethod>
      <code>sleepWithAfterClassAnnotation</code>
    </PossiblyUnusedMethod>
  </file>
  <file src="test/EndToEnd/Version09/TestCase/WithBeforeAnnotation/SleeperTest.php">
    <PossiblyUnusedMethod>
      <code>sleepWithBeforeAnnotation</code>
    </PossiblyUnusedMethod>
  </file>
  <file src="test/EndToEnd/Version09/TestCase/WithBeforeClassAnnotation/SleeperTest.php">
    <PossiblyUnusedMethod>
      <code>sleepWithBeforeClassAnnotation</code>
    </PossiblyUnusedMethod>
  </file>
  <file src="test/EndToEnd/Version09/TestMethod/WithRunInSeparateProcessAnnotation/SleeperTest.php">
    <PossiblyUnusedMethod>
      <code>sleepWithAfterAnnotation</code>
      <code>sleepWithAfterClassAnnotation</code>
      <code>sleepWithBeforeAnnotation</code>
      <code>sleepWithBeforeClassAnnotation</code>
    </PossiblyUnusedMethod>
  </file>
  <file src="test/EndToEnd/Version10/Configuration/Defaults/SleeperTest.php">
    <PossiblyUnusedMethod>
      <code>provideMillisecondsGreaterThanDefaultMaximumDuration</code>
    </PossiblyUnusedMethod>
  </file>
  <file src="test/EndToEnd/Version10/Configuration/MaximumCount/SleeperTest.php">
    <PossiblyUnusedMethod>
      <code>provideMillisecondsGreaterThanDefaultMaximumDuration</code>
    </PossiblyUnusedMethod>
  </file>
  <file src="test/EndToEnd/Version10/Configuration/MaximumDuration/SleeperTest.php">
    <PossiblyUnusedMethod>
      <code>provideMillisecondsGreaterThanMaximumDurationFromXmlConfiguration</code>
    </PossiblyUnusedMethod>
  </file>
  <file src="test/EndToEnd/Version10/Logger/WithConfigurationAndNoOption/SleeperTest.php">
    <PossiblyUnusedMethod>
      <code>provideMillisecondsGreaterThanDefaultMaximumDuration</code>
    </PossiblyUnusedMethod>
  </file>
  <file src="test/EndToEnd/Version10/Logger/WithConfigurationAndOption/SleeperTest.php">
    <PossiblyUnusedMethod>
      <code>provideMillisecondsGreaterThanDefaultMaximumDuration</code>
    </PossiblyUnusedMethod>
  </file>
  <file src="test/EndToEnd/Version10/Logger/WithNoConfigurationAndOption/SleeperTest.php">
    <PossiblyUnusedMethod>
      <code>provideMillisecondsGreaterThanDefaultMaximumDuration</code>
    </PossiblyUnusedMethod>
  </file>
  <file src="test/EndToEnd/Version10/TestCase/Bare/SleeperTest.php">
    <PossiblyUnusedMethod>
      <code>provideMillisecondsGreaterThanMaximumDurationFromXmlConfiguration</code>
    </PossiblyUnusedMethod>
  </file>
  <file src="test/EndToEnd/Version10/TestCase/Combination/SleeperTest.php">
    <PossiblyUnusedMethod>
      <code>provideMillisecondsGreaterThanMaximumDurationFromXmlConfiguration</code>
      <code>sleepWithAfterAnnotation</code>
      <code>sleepWithAfterAttribute</code>
      <code>sleepWithAfterClassAnnotation</code>
      <code>sleepWithAfterClassAttribute</code>
      <code>sleepWithBeforeAnnotation</code>
      <code>sleepWithBeforeAttribute</code>
      <code>sleepWithBeforeClassAnnotation</code>
      <code>sleepWithBeforeClassAttribute</code>
    </PossiblyUnusedMethod>
  </file>
  <file src="test/EndToEnd/Version10/TestCase/WithAfterAnnotation/SleeperTest.php">
    <PossiblyUnusedMethod>
      <code>provideMillisecondsGreaterThanMaximumDurationFromXmlConfiguration</code>
      <code>sleepWithAfterAnnotation</code>
    </PossiblyUnusedMethod>
  </file>
  <file src="test/EndToEnd/Version10/TestCase/WithAfterAttribute/SleeperTest.php">
    <PossiblyUnusedMethod>
      <code>provideMillisecondsGreaterThanMaximumDurationFromXmlConfiguration</code>
      <code>sleepWithAfterAttribute</code>
    </PossiblyUnusedMethod>
  </file>
  <file src="test/EndToEnd/Version10/TestCase/WithAfterClassAnnotation/SleeperTest.php">
    <PossiblyUnusedMethod>
      <code>provideMillisecondsGreaterThanMaximumDurationFromXmlConfiguration</code>
      <code>sleepWithAfterClassAnnotation</code>
    </PossiblyUnusedMethod>
  </file>
  <file src="test/EndToEnd/Version10/TestCase/WithAfterClassAttribute/SleeperTest.php">
    <PossiblyUnusedMethod>
      <code>provideMillisecondsGreaterThanMaximumDurationFromXmlConfiguration</code>
      <code>sleepWithAfterClassAttribute</code>
    </PossiblyUnusedMethod>
  </file>
  <file src="test/EndToEnd/Version10/TestCase/WithAssertPostConditions/SleeperTest.php">
    <PossiblyUnusedMethod>
      <code>provideMillisecondsGreaterThanMaximumDurationFromXmlConfiguration</code>
    </PossiblyUnusedMethod>
  </file>
  <file src="test/EndToEnd/Version10/TestCase/WithAssertPreConditions/SleeperTest.php">
    <PossiblyUnusedMethod>
      <code>provideMillisecondsGreaterThanMaximumDurationFromXmlConfiguration</code>
    </PossiblyUnusedMethod>
  </file>
  <file src="test/EndToEnd/Version10/TestCase/WithBeforeAnnotation/SleeperTest.php">
    <PossiblyUnusedMethod>
      <code>provideMillisecondsGreaterThanMaximumDurationFromXmlConfiguration</code>
      <code>sleepWithBeforeAnnotation</code>
    </PossiblyUnusedMethod>
  </file>
  <file src="test/EndToEnd/Version10/TestCase/WithBeforeAttribute/SleeperTest.php">
    <PossiblyUnusedMethod>
      <code>provideMillisecondsGreaterThanMaximumDurationFromXmlConfiguration</code>
      <code>sleepWithBeforeAttribute</code>
    </PossiblyUnusedMethod>
  </file>
  <file src="test/EndToEnd/Version10/TestCase/WithBeforeClassAnnotation/SleeperTest.php">
    <PossiblyUnusedMethod>
      <code>provideMillisecondsGreaterThanMaximumDurationFromXmlConfiguration</code>
      <code>sleepWithBeforeClassAnnotation</code>
    </PossiblyUnusedMethod>
  </file>
  <file src="test/EndToEnd/Version10/TestCase/WithBeforeClassAttribute/SleeperTest.php">
    <PossiblyUnusedMethod>
      <code>provideMillisecondsGreaterThanMaximumDurationFromXmlConfiguration</code>
      <code>sleepWithBeforeClassAttribute</code>
    </PossiblyUnusedMethod>
  </file>
  <file src="test/EndToEnd/Version10/TestCase/WithDataProvider/SleeperTest.php">
    <PossiblyUnusedMethod>
      <code>provideMillisecondsGreaterThanMaximumDurationFromXmlConfiguration</code>
    </PossiblyUnusedMethod>
  </file>
  <file src="test/EndToEnd/Version10/TestCase/WithSetUp/SleeperTest.php">
    <PossiblyUnusedMethod>
      <code>provideMillisecondsGreaterThanMaximumDurationFromXmlConfiguration</code>
    </PossiblyUnusedMethod>
  </file>
  <file src="test/EndToEnd/Version10/TestCase/WithSetUpBeforeClass/SleeperTest.php">
    <PossiblyUnusedMethod>
      <code>provideMillisecondsGreaterThanMaximumDurationFromXmlConfiguration</code>
    </PossiblyUnusedMethod>
  </file>
  <file src="test/EndToEnd/Version10/TestCase/WithTearDown/SleeperTest.php">
    <PossiblyUnusedMethod>
      <code>provideMillisecondsGreaterThanMaximumDurationFromXmlConfiguration</code>
    </PossiblyUnusedMethod>
  </file>
  <file src="test/EndToEnd/Version10/TestCase/WithTearDownAfterClass/SleeperTest.php">
    <PossiblyUnusedMethod>
      <code>provideMillisecondsGreaterThanMaximumDurationFromXmlConfiguration</code>
    </PossiblyUnusedMethod>
  </file>
  <file src="test/EndToEnd/Version10/TestMethod/WithRunInSeparateProcessAnnotation/SleeperTest.php">
    <PossiblyUnusedMethod>
      <code>sleepWithAfterAnnotation</code>
      <code>sleepWithAfterAttribute</code>
      <code>sleepWithAfterClassAnnotation</code>
      <code>sleepWithAfterClassAttribute</code>
      <code>sleepWithBeforeAnnotation</code>
      <code>sleepWithBeforeAttribute</code>
      <code>sleepWithBeforeClassAnnotation</code>
      <code>sleepWithBeforeClassAttribute</code>
    </PossiblyUnusedMethod>
  </file>
  <file src="test/EndToEnd/Version10/TestMethod/WithRunInSeparateProcessAttribute/SleeperTest.php">
    <PossiblyUnusedMethod>
      <code>sleepWithAfterAnnotation</code>
      <code>sleepWithAfterAttribute</code>
      <code>sleepWithAfterClassAnnotation</code>
      <code>sleepWithAfterClassAttribute</code>
      <code>sleepWithBeforeAnnotation</code>
      <code>sleepWithBeforeAttribute</code>
      <code>sleepWithBeforeClassAnnotation</code>
      <code>sleepWithBeforeClassAttribute</code>
    </PossiblyUnusedMethod>
  </file>
  <file src="test/EndToEnd/Version11/Configuration/Defaults/SleeperTest.php">
    <PossiblyUnusedMethod>
      <code>provideMillisecondsGreaterThanDefaultMaximumDuration</code>
    </PossiblyUnusedMethod>
  </file>
  <file src="test/EndToEnd/Version11/Configuration/MaximumCount/SleeperTest.php">
    <PossiblyUnusedMethod>
      <code>provideMillisecondsGreaterThanDefaultMaximumDuration</code>
    </PossiblyUnusedMethod>
  </file>
  <file src="test/EndToEnd/Version11/Configuration/MaximumDuration/SleeperTest.php">
    <PossiblyUnusedMethod>
      <code>provideMillisecondsGreaterThanMaximumDurationFromXmlConfiguration</code>
    </PossiblyUnusedMethod>
  </file>
  <file src="test/EndToEnd/Version11/Logger/WithConfigurationAndNoOption/SleeperTest.php">
    <PossiblyUnusedMethod>
      <code>provideMillisecondsGreaterThanDefaultMaximumDuration</code>
    </PossiblyUnusedMethod>
  </file>
  <file src="test/EndToEnd/Version11/Logger/WithConfigurationAndOption/SleeperTest.php">
    <PossiblyUnusedMethod>
      <code>provideMillisecondsGreaterThanDefaultMaximumDuration</code>
    </PossiblyUnusedMethod>
  </file>
  <file src="test/EndToEnd/Version11/Logger/WithNoConfigurationAndOption/SleeperTest.php">
    <PossiblyUnusedMethod>
      <code>provideMillisecondsGreaterThanDefaultMaximumDuration</code>
    </PossiblyUnusedMethod>
  </file>
  <file src="test/EndToEnd/Version11/TestCase/Bare/SleeperTest.php">
    <PossiblyUnusedMethod>
      <code>provideMillisecondsGreaterThanMaximumDurationFromXmlConfiguration</code>
    </PossiblyUnusedMethod>
  </file>
  <file src="test/EndToEnd/Version11/TestCase/Combination/SleeperTest.php">
    <PossiblyUnusedMethod>
      <code>provideMillisecondsGreaterThanMaximumDurationFromXmlConfiguration</code>
      <code>sleepWithAfterAttribute</code>
      <code>sleepWithAfterClassAttribute</code>
      <code>sleepWithBeforeAttribute</code>
      <code>sleepWithBeforeClassAttribute</code>
    </PossiblyUnusedMethod>
  </file>
  <file src="test/EndToEnd/Version11/TestCase/WithAfterAttribute/SleeperTest.php">
    <PossiblyUnusedMethod>
      <code>provideMillisecondsGreaterThanMaximumDurationFromXmlConfiguration</code>
      <code>sleepWithAfterAttribute</code>
    </PossiblyUnusedMethod>
  </file>
  <file src="test/EndToEnd/Version11/TestCase/WithAfterClassAttribute/SleeperTest.php">
    <PossiblyUnusedMethod>
      <code>provideMillisecondsGreaterThanMaximumDurationFromXmlConfiguration</code>
      <code>sleepWithAfterClassAttribute</code>
    </PossiblyUnusedMethod>
  </file>
  <file src="test/EndToEnd/Version11/TestCase/WithAssertPostConditions/SleeperTest.php">
    <PossiblyUnusedMethod>
      <code>provideMillisecondsGreaterThanMaximumDurationFromXmlConfiguration</code>
    </PossiblyUnusedMethod>
  </file>
  <file src="test/EndToEnd/Version11/TestCase/WithAssertPreConditions/SleeperTest.php">
    <PossiblyUnusedMethod>
      <code>provideMillisecondsGreaterThanMaximumDurationFromXmlConfiguration</code>
    </PossiblyUnusedMethod>
  </file>
  <file src="test/EndToEnd/Version11/TestCase/WithBeforeAttribute/SleeperTest.php">
    <PossiblyUnusedMethod>
      <code>provideMillisecondsGreaterThanMaximumDurationFromXmlConfiguration</code>
      <code>sleepWithBeforeAttribute</code>
    </PossiblyUnusedMethod>
  </file>
  <file src="test/EndToEnd/Version11/TestCase/WithBeforeClassAttribute/SleeperTest.php">
    <PossiblyUnusedMethod>
      <code>provideMillisecondsGreaterThanMaximumDurationFromXmlConfiguration</code>
      <code>sleepWithBeforeClassAttribute</code>
    </PossiblyUnusedMethod>
  </file>
  <file src="test/EndToEnd/Version11/TestCase/WithDataProvider/SleeperTest.php">
    <PossiblyUnusedMethod>
      <code>provideMillisecondsGreaterThanMaximumDurationFromXmlConfiguration</code>
    </PossiblyUnusedMethod>
  </file>
  <file src="test/EndToEnd/Version11/TestCase/WithSetUp/SleeperTest.php">
    <PossiblyUnusedMethod>
      <code>provideMillisecondsGreaterThanMaximumDurationFromXmlConfiguration</code>
    </PossiblyUnusedMethod>
  </file>
  <file src="test/EndToEnd/Version11/TestCase/WithSetUpBeforeClass/SleeperTest.php">
    <PossiblyUnusedMethod>
      <code>provideMillisecondsGreaterThanMaximumDurationFromXmlConfiguration</code>
    </PossiblyUnusedMethod>
  </file>
  <file src="test/EndToEnd/Version11/TestCase/WithTearDown/SleeperTest.php">
    <PossiblyUnusedMethod>
      <code>provideMillisecondsGreaterThanMaximumDurationFromXmlConfiguration</code>
    </PossiblyUnusedMethod>
  </file>
  <file src="test/EndToEnd/Version11/TestCase/WithTearDownAfterClass/SleeperTest.php">
    <PossiblyUnusedMethod>
      <code>provideMillisecondsGreaterThanMaximumDurationFromXmlConfiguration</code>
    </PossiblyUnusedMethod>
  </file>
  <file src="test/EndToEnd/Version11/TestMethod/WithRunInSeparateProcessAttribute/SleeperTest.php">
    <PossiblyUnusedMethod>
      <code>sleepWithAfterAttribute</code>
      <code>sleepWithAfterClassAttribute</code>
      <code>sleepWithBeforeAttribute</code>
      <code>sleepWithBeforeClassAttribute</code>
    </PossiblyUnusedMethod>
  </file>
  <file src="test/Fixture/Sleeper.php">
    <ArgumentTypeCoercion>
      <code><![CDATA[$this->milliseconds * 1000]]></code>
    </ArgumentTypeCoercion>
  </file>
  <file src="test/Unit/Collector/DefaultCollectorTest.php">
    <MixedArgument>
      <code><![CDATA[$faker->filePath()]]></code>
      <code><![CDATA[$faker->filePath()]]></code>
      <code><![CDATA[$faker->filePath()]]></code>
      <code><![CDATA[$faker->filePath()]]></code>
      <code><![CDATA[$faker->filePath()]]></code>
      <code><![CDATA[$faker->filePath()]]></code>
    </MixedArgument>
  </file>
  <file src="test/Unit/Reporter/DefaultReporterTest.php">
    <MixedInferredReturnType>
      <code>iterable</code>
    </MixedInferredReturnType>
  </file>
  <file src="test/Unit/SlowTestTest.php">
    <MixedArgument>
      <code><![CDATA[$faker->filePath()]]></code>
    </MixedArgument>
  </file>
</files>
